py/__init__.py
py/cli.py
pydepman-0.1.0.dist-info/METADATA
pydepman-0.1.0.dist-info/WHEEL
pydepman-0.1.0.dist-info/entry_points.txt
pydepman-0.1.0.dist-info/top_level.txt
pydepman-0.1.0.dist-info/RECORD
