Metadata-Version: 2.1
Name: pydepman
Version: 0.1.0
Summary: A modern dependency manager for Python
Home-page: https://github.com/pavelsof/py
Author: Pavel Sofroniev
Author-email: mail@pavelsof.com
License: UNKNOWN
Project-URL: Source, https://github.com/pavelsof/py
Project-URL: Tracker, https://github.com/pavelsof/py/issues
Keywords: dependency manager
Platform: UNKNOWN
Classifier: Development Status :: 1 - Planning
Classifier: Environment :: Console
Classifier: Intended Audience :: Developers
Classifier: License :: OSI Approved :: GNU General Public License v3 (GPLv3)
Classifier: Programming Language :: Python :: 3
Classifier: Topic :: Software Development
Requires-Python: >=3
